Metadata-Version: 1.1
Name: nttnoperations
Version: 0.0.2
Summary: Basic math operations
Home-page: UNKNOWN
Author: nttnhannho
Author-email: nttnhannho@gmail.com
License: MIT
Keywords: operations
Platform: UNKNOWN
Classifier: Development Status :: 5 - Production/Stable
Classifier: Intended Audience :: Education
Classifier: Operating System :: Microsoft :: Windows :: Windows 10
Classifier: License :: OSI Approved :: MIT License
Classifier: Programming Language :: Python :: 3
